ipyblob/__init__.py
ipydb/base.py
ipydb/duckdb.py
ipydata-0.1.4.dist-info/METADATA
ipydata-0.1.4.dist-info/WHEEL
ipydata-0.1.4.dist-info/licenses/LICENSE
ipydata-0.1.4.dist-info/RECORD
