Metadata-Version: 2.4
Name: ipydata
Version: 0.1.4
Summary: Simple interactive database and blob storage operations in python.
Project-URL: Source, https://github.com/j-blackwell/ipydata
Author-email: James Blackwell <33688964+j-blackwell@users.noreply.github.com>
License: MIT License
License-File: LICENSE
Requires-Python: >=3.12
Requires-Dist: duckdb>=1.3.2
Requires-Dist: numpy>=2.3.2
Requires-Dist: pandas>=2.3.1
